LANCommunicate/__init__.py
LANCommunicate/exception.py
LANCommunicate/nat_connector.py
LANCommunicate/net_tools.py
LANCommunicate/say_hello.py
LANCommunicate/static.py
LANCommunicate-0.1.dist-info/LICENSE
LANCommunicate-0.1.dist-info/METADATA
LANCommunicate-0.1.dist-info/WHEEL
LANCommunicate-0.1.dist-info/top_level.txt
LANCommunicate-0.1.dist-info/RECORD
